QuantRiskTools/FittedModels.py
QuantRiskTools/MatrixPSDFixers.py
QuantRiskTools/PortAnalytics.py
QuantRiskTools/VaRCalculations.py
QuantRiskTools/__init__.py
QuantRiskTools/calculateReturnsAndSimulatedValues.py
QuantRiskBookTools-0.1.dist-info/METADATA
QuantRiskBookTools-0.1.dist-info/WHEEL
QuantRiskBookTools-0.1.dist-info/top_level.txt
QuantRiskBookTools-0.1.dist-info/RECORD
