Metadata-Version: 2.1
Name: QuantRiskBookTools
Version: 0.1
Summary: Description of your package
Home-page: https://github.com/MEstrada21/FinTech-545-Spring2023/tree/main/QuantRiskBookTools
Author: Your Name
Author-email: UNKNOWN
License: UNKNOWN
Platform: UNKNOWN
Classifier: Programming Language :: Python :: 3
Classifier: License :: OSI Approved :: MIT License
Classifier: Operating System :: OS Independent
Requires-Dist: numpy
Requires-Dist: pandas
Requires-Dist: scipy
Requires-Dist: sklearn
Requires-Dist: matplotlib
